javdb/__main__.py
javdb-0.1.2.dist-info/licenses/LICENSE
javdb-0.1.2.dist-info/METADATA
javdb-0.1.2.dist-info/WHEEL
javdb-0.1.2.dist-info/entry_points.txt
javdb-0.1.2.dist-info/top_level.txt
javdb-0.1.2.dist-info/RECORD
