Metadata-Version: 2.4
Name: javdb
Version: 0.1.2
Summary: Command-line scraper for javdatabase.com. Search movies, extract metadata, and download preview images or NFO files for media centers.
Author-email: Phoenixthrush UwU <contact@phoenixthrush.com>
Maintainer-email: Phoenixthrush UwU <contact@phoenixthrush.com>
License-Expression: MIT
Project-URL: Homepage, https://github.com/phoenixthrush/javdb-python
Project-URL: Documentation, https://github.com/phoenixthrush/javdb-python/blob/main/README.md
Project-URL: Repository, https://github.com/phoenixthrush/javdb-python.git
Project-URL: Bug Tracker, https://github.com/phoenixthrush/javdb-python/issues
Project-URL: Changelog, https://github.com/phoenixthrush/javdb-python/commits
Project-URL: Source Code, https://github.com/phoenixthrush/javdb-python
Project-URL: Download, https://github.com/phoenixthrush/javdb-python/archive/refs/heads/main.zip
Project-URL: Funding, https://github.com/sponsors/phoenixthrush
Keywords: javdatabase,movies,metadata,preview,images
Classifier: Development Status :: 4 - Beta
Classifier: Programming Language :: Python
Requires-Python: >=3.7
License-File: LICENSE
Requires-Dist: niquests
Dynamic: license-file
